tabstar/__init__.py
tabstar/constants.py
tabstar/tabstar_datasets.py
tabstar/tabstar_model.py
tabstar/tabstar_verbalizer.py
tabstar/arch/__init__.py
tabstar/arch/arch.py
tabstar/arch/config.py
tabstar/arch/fusion.py
tabstar/arch/interaction.py
tabstar/arch/prediction.py
tabstar/datasets/__init__.py
tabstar/datasets/all_datasets.py
tabstar/preprocessing/__init__.py
tabstar/preprocessing/binning.py
tabstar/preprocessing/dates.py
tabstar/preprocessing/detection.py
tabstar/preprocessing/feat_types.py
tabstar/preprocessing/nulls.py
tabstar/preprocessing/scaler.py
tabstar/preprocessing/sparse.py
tabstar/preprocessing/splits.py
tabstar/preprocessing/target.py
tabstar/preprocessing/texts.py
tabstar/preprocessing/verbalize.py
tabstar/resources/imdb.csv
tabstar/training/__init__.py
tabstar/training/checkpoint_averaging.py
tabstar/training/dataloader.py
tabstar/training/devices.py
tabstar/training/early_stopping.py
tabstar/training/hyperparams.py
tabstar/training/lora.py
tabstar/training/metrics.py
tabstar/training/optimizer.py
tabstar/training/trainer.py
tabstar/training/utils.py
tabstar-1.1.15.dist-info/METADATA
tabstar-1.1.15.dist-info/WHEEL
tabstar-1.1.15.dist-info/top_level.txt
tabstar-1.1.15.dist-info/RECORD
