Metadata-Version: 2.4
Name: tabstar
Version: 1.1.15
Summary: TabSTAR: A Foundation Tabular Model With Semantically Target-Aware Representations
Author-email: Alan Arazi <alanarazi7@gmail.com>
License: MIT
Requires-Python: >=3.10
Requires-Dist: joblib
Requires-Dist: numpy
Requires-Dist: pandas>=2.2.2
Requires-Dist: peft
Requires-Dist: scikit-learn
Requires-Dist: skrub
Requires-Dist: torch>=2.6.0
Requires-Dist: tqdm
Requires-Dist: transformers>=4.49.0
